aiida_testing/__init__.py
aiida_testing/_config.py
aiida_testing/py.typed
aiida_testing/export_cache/__init__.py
aiida_testing/mock_code/__init__.py
aiida_testing/mock_code/_cli.py
aiida_testing/mock_code/_env_keys.py
aiida_testing/mock_code/_fixtures.py
aiida_testing/mock_code/_hasher.py
aiida_testing_dev-0.1.0.dev1.dist-info/entry_points.txt
aiida_testing_dev-0.1.0.dev1.dist-info/LICENSE.txt
aiida_testing_dev-0.1.0.dev1.dist-info/WHEEL
aiida_testing_dev-0.1.0.dev1.dist-info/METADATA
aiida_testing_dev-0.1.0.dev1.dist-info/RECORD
